agent_workflows/__init__.py
agent_workflows/cli.py
agent_workflows/dag.py
agent_workflows/engine.py
agent_workflows/parser.py
agent_workflows/resolver.py
agent_workflows/plugins/__init__.py
agent_workflows/plugins/agents/__init__.py
agent_workflows/plugins/agents/claude_code.py
agent_workflows/plugins/agents/general.py
agent_workflows/plugins/agents/structured.py
agent_workflows/plugins/audio/__init__.py
agent_workflows/plugins/audio/stt.py
agent_workflows/plugins/audio/tts.py
agent_workflows/plugins/git/__init__.py
agent_workflows/plugins/git/download.py
agent_workflows/plugins/git/push.py
agent_workflows/plugins/templates/__init__.py
agent_workflows/plugins/templates/match.py
agent_workflows/plugins/terminal/__init__.py
agent_workflows/plugins/terminal/run.py
agent_workflows/plugins/terminal/script.py
agent_workflows/workflows/__init__.py
agent_workflows/workflows/apply-template.agent-workflow.yml
agent_workflows/workflows/example.agent-workflow.yml
agent_workflows/workflows/speech-input.agent-workflow.yml
siili_agent_workflows-0.3.0.dist-info/METADATA
siili_agent_workflows-0.3.0.dist-info/WHEEL
siili_agent_workflows-0.3.0.dist-info/entry_points.txt
siili_agent_workflows-0.3.0.dist-info/RECORD
