Metadata-Version: 2.4
Name: siili-agent-workflows
Version: 0.3.0
Summary: YAML-driven workflow engine for AI agents
Project-URL: Homepage, https://github.com/siilisolutions/siili-ai-sdk
Project-URL: Repository, https://github.com/siilisolutions/siili-ai-sdk
Author-email: Siili Solutions Oyj <info@siili.com>
License-Expression: MIT
Keywords: agents,ai,automation,developer-tools,workflows,yaml
Classifier: Development Status :: 3 - Alpha
Classifier: Intended Audience :: Developers
Classifier: License :: OSI Approved :: MIT License
Classifier: Programming Language :: Python :: 3
Classifier: Programming Language :: Python :: 3.10
Classifier: Programming Language :: Python :: 3.11
Classifier: Programming Language :: Python :: 3.12
Classifier: Topic :: Scientific/Engineering :: Artificial Intelligence
Classifier: Topic :: Software Development
Requires-Python: >=3.10
Requires-Dist: click>=8.0
Requires-Dist: numpy>=1.24.0
Requires-Dist: platformdirs>=4.0
Requires-Dist: pydub>=0.25.1
Requires-Dist: python-dotenv>=1.0
Requires-Dist: pyyaml>=6.0
Requires-Dist: scipy>=1.11.0
Requires-Dist: siili-ai-sdk>=0.2.0
Requires-Dist: siili-coding-agents>=0.2.0
Requires-Dist: sounddevice>=0.4.6
Provides-Extra: audio
Requires-Dist: numpy>=1.24.0; extra == 'audio'
Requires-Dist: pydub>=0.25.1; extra == 'audio'
Requires-Dist: scipy>=1.11.0; extra == 'audio'
Requires-Dist: sounddevice>=0.4.6; extra == 'audio'
Provides-Extra: dev
Requires-Dist: pytest-asyncio>=0.21.1; extra == 'dev'
Requires-Dist: pytest>=7.4.0; extra == 'dev'
Requires-Dist: ruff; extra == 'dev'
Requires-Dist: ty; extra == 'dev'
